cdk_bucket_deployment_expirator/__init__.py
cdk_bucket_deployment_expirator/py.typed
cdk_bucket_deployment_expirator/_jsii/__init__.py
cdk_bucket_deployment_expirator/_jsii/cdk-bucket-deployment-expirator@1.87.1.jsii.tgz
cdk_bucket_deployment_expirator-1.87.1.dist-info/METADATA
cdk_bucket_deployment_expirator-1.87.1.dist-info/WHEEL
cdk_bucket_deployment_expirator-1.87.1.dist-info/top_level.txt
cdk_bucket_deployment_expirator-1.87.1.dist-info/RECORD
