Metadata-Version: 2.1
Name: cdk-bucket-deployment-expirator
Version: 1.87.1
Summary: Opinionated CDK Bucket Deployment object pruner for maintaining N old versions
Home-page: https://github.com/kcwinner/cdk-bucket-deployment-expirator.git
Author: Ken Winner<kcswinner@gmail.com>
License: Apache-2.0
Project-URL: Source, https://github.com/kcwinner/cdk-bucket-deployment-expirator.git
Platform: UNKNOWN
Classifier: Intended Audience :: Developers
Classifier: Operating System :: OS Independent
Classifier: Programming Language :: JavaScript
Classifier: Programming Language :: Python :: 3 :: Only
Classifier: Programming Language :: Python :: 3.6
Classifier: Programming Language :: Python :: 3.7
Classifier: Programming Language :: Python :: 3.8
Classifier: Programming Language :: Python :: 3.9
Classifier: Typing :: Typed
Classifier: Development Status :: 5 - Production/Stable
Classifier: License :: OSI Approved
Requires-Python: >=3.6
Requires-Dist: aws-cdk.aws-iam (<2.0.0,>=1.87.1)
Requires-Dist: aws-cdk.aws-lambda-nodejs (<2.0.0,>=1.87.1)
Requires-Dist: aws-cdk.aws-lambda (<2.0.0,>=1.87.1)
Requires-Dist: aws-cdk.aws-s3-deployment (<2.0.0,>=1.87.1)
Requires-Dist: aws-cdk.aws-s3 (<2.0.0,>=1.87.1)
Requires-Dist: aws-cdk.core (<2.0.0,>=1.87.1)
Requires-Dist: constructs (<4.0.0,>=3.2.27)
Requires-Dist: jsii (<2.0.0,>=1.15.0)
Requires-Dist: publication (>=0.0.3)
